mmer/__init__.py
mmer/core/__init__.py
mmer/core/mixed_effect.py
mmer/core/mixed_result.py
mmer/core/operator.py
mmer/core/terms.py
mmer/lanczos_algorithm/__init__.py
mmer/lanczos_algorithm/slq.py
mmer/utils/__init__.py
mmer/utils/multi_output.py
mmer-1.0.0.dist-info/licenses/LICENSE
mmer-1.0.0.dist-info/METADATA
mmer-1.0.0.dist-info/WHEEL
mmer-1.0.0.dist-info/top_level.txt
mmer-1.0.0.dist-info/RECORD
