Metadata-Version: 2.4
Name: mmer
Version: 1.0.0
Summary: MMER: Multivariate Mixed Effects Regression.
Author-email: Sajad Hussaini <hussaini.smsajad@gmail.com>
License-Expression: MIT
Project-URL: Homepage, https://github.com/Sajad-Hussaini/mmer
Project-URL: Repository, https://github.com/Sajad-Hussaini/mmer
Project-URL: Issues, https://github.com/Sajad-Hussaini/mmer/issues
Keywords: mmer,multivariate regression,mixed-effects,machine-learning,uncertainty quantification,ground motion models,earthquake engineering
Classifier: Programming Language :: Python :: 3
Classifier: Operating System :: OS Independent
Classifier: Intended Audience :: Science/Research
Classifier: Topic :: Scientific/Engineering
Requires-Python: >=3.10
License-File: LICENSE
Requires-Dist: numpy
Requires-Dist: scipy
Requires-Dist: joblib
Requires-Dist: matplotlib
Requires-Dist: scikit-learn
Requires-Dist: tqdm
Requires-Dist: sphinx
Requires-Dist: sphinx_rtd_theme
Requires-Dist: myst-parser
Requires-Dist: nbsphinx
Dynamic: license-file
